antchain_sdk_ak_d3c4f09125a14cd587057c405561809a/__init__.py
antchain_sdk_ak_d3c4f09125a14cd587057c405561809a/client.py
antchain_sdk_ak_d3c4f09125a14cd587057c405561809a/models.py
antchain_ak_d3c4f09125a14cd587057c405561809a-1.1.3.dist-info/LICENSE
antchain_ak_d3c4f09125a14cd587057c405561809a-1.1.3.dist-info/METADATA
antchain_ak_d3c4f09125a14cd587057c405561809a-1.1.3.dist-info/WHEEL
antchain_ak_d3c4f09125a14cd587057c405561809a-1.1.3.dist-info/top_level.txt
antchain_ak_d3c4f09125a14cd587057c405561809a-1.1.3.dist-info/RECORD
